setup.py
japanize_matplotlib/__init__.py
japanize_matplotlib.egg-info/PKG-INFO
japanize_matplotlib.egg-info/SOURCES.txt
japanize_matplotlib.egg-info/dependency_links.txt
japanize_matplotlib.egg-info/top_level.txt